servizio_anon/__init__.py
servizio_anon/servizio_anon.py
servizio_anon-0.5.2.dist-info/LICENSE.md
servizio_anon-0.5.2.dist-info/METADATA
servizio_anon-0.5.2.dist-info/WHEEL
servizio_anon-0.5.2.dist-info/top_level.txt
servizio_anon-0.5.2.dist-info/RECORD
