Metadata-Version: 2.1
Name: servizio_anon
Version: 0.5.2
Summary: Aggiornamento automatico di documenti GateNLP mediante Presidio
Home-page: https://github.com/RafVale/anon_testo
Author: Raffaele Valendino
Author-email: raffaele.valendino@gmail.com
License: MIT
Classifier: Development Status :: 1 - Planning
Classifier: Intended Audience :: Education
Classifier: License :: OSI Approved :: MIT License
Classifier: Operating System :: Microsoft :: Windows :: Windows 10
Classifier: Programming Language :: Python :: 3.9
License-File: LICENSE.md
Requires-Dist: spacy <=3.2.0
Requires-Dist: presidio-analyzer <=2.2.25
Requires-Dist: presidio-anonymizer <=2.2.25
Requires-Dist: typing-inspect ==0.8.0
Requires-Dist: typing-extensions ==4.5.0
Requires-Dist: anon-testo >=0.5.0
